wws_api/__init__.py
wws_api/process_data.py
wws_api/request_data.py
wws_api-0.1.2.dist-info/WHEEL
wws_api-0.1.2.dist-info/METADATA
wws_api-0.1.2.dist-info/RECORD
