Metadata-Version: 2.3
Name: wws-api
Version: 0.1.2
Summary: Simplifies the process for calling the Workday Web Services API asyncronously.
Requires-Dist: aiohttp>=3.12.15
Requires-Dist: lxml>=6.0.0
Requires-Dist: pyarrow>=21.0.0
Requires-Dist: xmltodict>=0.14.2
Requires-Python: >=3.11
